Workbook

Sheet Intro
B1: 9-11
C2: Crydon Inc. manufactures an advanced swim fin for scuba divers. Management is now preparing detailed budgets for the third quarter, July through September and has assembled the following information to assist in preparing the budget:
B7: a) | C7: The marketing Department has estimated sales as follows for the remainder of the year (pairs of swim fins):
C11: July | D11: 6000
C12: August | D12: 7000
C13: September | D13: 5000
C14: October | D14: 4000
C15: November | D15: 3000
C16: December | D16: 3000
C18: The selling price of the swim fins is $50 per pair.
B20: b) | C20: All sales are on account. Based on past experience, sales are expected to be collected in the following pattern:
C24: • 40% in the month of sale
C25: • 50% in the month following the sale
C26: • 10% uncollectible
C28: The AR balance on July 1st (excluding the uncollectible portion) was $130,000.
B30: c) | C30: The company maintains finished goods inventories equal to 10% of the following month’s sales. The inventory of finished goods on July 1st will be 600 pairs.
B34: d) | C34: Each pair of swim fins requires 2 pounds of grelco compound. To prevent shortages, the company would like the inventory of grelco compound on hand at the end of each month to be equal to 20% of the following month’s production needs. The inventory of grelco compound on hand on July 1 will be 2,440kg.
B40: c) | C40: Grelco compound costs $2.50 per kg. Crydon pays of 60% of its purchases in the month of purchase, the remainder is paid for in the following month. The accounts payable balance for grelco compound purchases will be $11,400 on July 1st.

Sheet 1) Sales Budget
B2: 1) | C2: Prepare a sales budget, by month and in total for the third quarter.
C7: The sales budget is the starting point for preparing the master budget. The sales budget considers the budgeted sales in units * the selling price.
D11: July | E11: August | F11: September | G11: Quarter
C12: Budgeted sales (pairs) | D12: =Intro!D11 -> 6000 | E12: =Intro!D12 -> 7000 | F12: =Intro!D13 -> 5000 | G12: =SUM(D12:F12) -> 18000
C13: Selling price per pair | D13: 50 | E13: 50 | F13: 50 | G13: 50
C14: Total budgeted sales | D14: =D12*D13 -> 300000 | E14: =E12*E13 -> 350000 | F14: =F12*F13 -> 250000 | G14: =SUM(D14:F14) -> 900000

Sheet 2) Cash Collection
B2: 2) | C2: Prepare a schedule of expected cash collection by month and in total for the third quarter.
C7: The schedule of expected cash collection will be necessary to prepare a cash budget. This computation will help us determine how much cash the company can expect to collect from their sales. The computations in this budget will be dependent on the results of the sales budget. If there is a cash shortfall for any given period, the company must address how they will address this issue. The company will need to borrow or find an alternative source of cash to ensure their operations can continue.
D17: July | E17: August | F17: September | G17: Quarter
C18: A/R: Beginning | D18: 130000 | G18: =SUM(D18:F18) -> 130000
C19: July Sales | D19: =0.4*Intro!D11*50 -> 120000 | E19: =0.5*Intro!D11*50 -> 150000 | G19: =SUM(D19:F19) -> 270000
C20: August Sales | E20: =0.4*Intro!D12*50 -> 140000 | F20: =0.5*Intro!D12*50 -> 175000 | G20: =SUM(D20:F20) -> 315000
C21: September Sales | F21: =0.4*Intro!D13*50 -> 100000 | G21: =SUM(D21:F21) -> 100000
C22: Total budgeted sales | D22: =SUM(D18:D21) -> 250000 | E22: =SUM(E18:E21) -> 290000 | F22: =SUM(F18:F21) -> 275000 | G22: =SUM(G18:G21) -> 815000

Sheet 3) Production Budget
B2: 3) | C2: Prepare a production budget for each of the months July through October.
C7: The production budget shows the number of units that must be produced for a given budget period. It must be prepared after the sales budget as it incorporate the budgeted sales quantities and consideration to beginning and ending inventory must also be given.
D13: July | E13: August | F13: September | G13: October | H13: November | I13: Quarter
C14: Budgeted Sales | D14: =Intro!D11 -> 6000 | E14: =Intro!D12 -> 7000 | F14: =Intro!D13 -> 5000 | G14: =Intro!D14 -> 4000 | H14: =Intro!D15 -> 3000 | I14: =SUM(D14:F14) -> 18000
C15: + Desired Ending Inv. | D15: =0.1*E14 -> 700 | E15: =0.1*F14 -> 500 | F15: =0.1*G14 -> 400 | G15: =0.1*H14 -> 300 | I15: =SUM(D15:F15) -> 1600
C16: Total Units Needed | D16: =SUM(D14:D15) -> 6700 | E16: =SUM(E14:E15) -> 7500 | F16: =SUM(F14:F15) -> 5400 | G16: =SUM(G14:G15) -> 4300 | I16: =SUM(D16:F16) -> 19600
C17: - Beg. Inventory | D17: =0.1*D14 -> 600 | E17: =0.1*E14 -> 700 | F17: =0.1*F14 -> 500 | G17: =0.1*G14 -> 400 | I17: =SUM(D17:F17) -> 1800
C19: Required Production units | D19: =D14+D15-D17 -> 6100 | E19: =E14+E15-E17 -> 6800 | F19: =F14+F15-F17 -> 4900 | G19: =G14+G15-G17 -> 3900 | I19: =SUM(D19:F19) -> 17800

Sheet 4) DM Purchases Budget
B2: 4) | C2: Prepare a Direct Materials Purchases Budget by month and in total for the third quarter:
C7: The direct materials purchases budget shows the amount of raw materials that must be purchased for a given budget period. It must be prepared after the production budget as it will be based on the required units of productions. In this case, it is important to determine how much grelco is needed for a pair of fins (unit of production) as well as how much grelco is required in inventory.
D15: July | E15: August | F15: September | G15: October | H15: Quarter
C16: Budgeted Production | D16: ='3) Production Budget'!D19 -> 6100 | E16: ='3) Production Budget'!E19 -> 6800 | F16: ='3) Production Budget'!F19 -> 4900 | G16: ='3) Production Budget'!G19 -> 3900 | H16: =SUM(D16:F16) -> 17800
C17: DM needed per unit | D17: 2 | E17: 2 | F17: 2 | G17: 2 | H17: 2
C18: Grelco needed for production | D18: =D16*D17 -> 12200 | E18: =E16*E17 -> 13600 | F18: =F16*F17 -> 9800 | G18: =G16*G17 -> 7800 | H18: =SUM(D18:F18) -> 35600
C19: Add ending Inventory | D19: =0.2*E18 -> 2720 | E19: =0.2*F18 -> 1960 | F19: =0.2*G18 -> 1560 | H19: =F19 -> 1560
C21: TOTAL GRELCO NEEDS | D21: =SUM(D18:D19) -> 14920 | E21: =SUM(E18:E19) -> 15560 | F21: =SUM(F18:F19) -> 11360 | H21: =SUM(H18:H19) -> 37160
C23: Less Beg. Inventory | D23: =0.2*D18 -> 2440 | E23: =0.2*E18 -> 2720 | F23: =0.2*F18 -> 1960 | H23: =D23 -> 2440
C24: Grelco to Purchase (lbs) | D24: =D21-D23 -> 12480 | E24: =E21-E23 -> 12840 | F24: =F21-F23 -> 9400 | H24: =H21-H23 -> 34720
C26: Cost of Raw Materials purchases (@$2.5/lbs) | D26: =D24*2.5 -> 31200 | E26: =E24*2.5 -> 32100 | F26: =F24*2.5 -> 23500 | H26: =H24*2.5 -> 86800

Sheet 5) Cash Disbursements
B2: 4) | C2: Prepare a schedule of cash disbursements by month and in total for the third quarter.
D7: July | E7: August | F7: September | G7: Quarter
C8: AP: Beginning of Period | D8: 11400 | G8: =SUM(D8:F8) -> 11400
C9: July Purchases | D9: ='4) DM Purchases Budget'!D26*0.6 -> 18720 | E9: ='4) DM Purchases Budget'!D26*0.4 -> 12480 | G9: =SUM(D9:F9) -> 31200
C10: August Purchases | E10: ='4) DM Purchases Budget'!E26*0.6 -> 19260 | F10: ='4) DM Purchases Budget'!E26*0.4 -> 12840 | G10: =SUM(D10:F10) -> 32100
C11: September purchases | F11: ='4) DM Purchases Budget'!F26*0.6 -> 14100 | G11: =SUM(D11:F11) -> 14100
C12: Total Cash Disbursement | D12: =SUM(D8:D11) -> 30120 | E12: =SUM(E8:E11) -> 31740 | F12: =SUM(F8:F11) -> 26940 | G12: =SUM(D12:F12) -> 88800

Sheet 6) Manufacturing OH Budget
B2: 6) | C2: Prepare a Manufacturing Overhead Budget with the related cash disbursement by month and in total for the third quarter
C7: In the production of fins, Crydon incurs a cost of $0.4 of variable OH cost per unit and their estimated MOH for the current year is $875,000. The MOH are allocated based on the units produced and the budgeted total units for the year has been set at 65,000 units. From the total fixed MOH, $240,000 relate to depreciation.
D15: July | E15: August | F15: September | G15: Quarter
C16: Budgeted Units | D16: ='4) DM Purchases Budget'!D16 -> 6100 | E16: ='4) DM Purchases Budget'!E16 -> 6800 | F16: ='4) DM Purchases Budget'!F16 -> 4900 | G16: =SUM(D16:F16) -> 17800
C17: Variable OH rate | D17: 0.4 | E17: 0.4 | F17: 0.4 | G17: 0.4
C19: Total Variable MOH | D19: =D16*D17 -> 2440 | E19: =E16*E17 -> 2720 | F19: =F16*F17 -> 1960 | G19: =G16*G17 -> 7120
C21: Fixed OH per month ($875,000/12) | D21: =875000/12 -> 72916.667 | E21: =875000/12 -> 72916.667 | F21: =875000/12 -> 72916.667 | G21: =SUM(D21:F21) -> 218750
C23: Total MOH | D23: =SUM(D19:D21) -> 75356.667 | E23: =SUM(E19:E21) -> 75636.667 | F23: =SUM(F19:F21) -> 74876.667 | G23: =SUM(G19:G21) -> 225870
C25: Less Depreciation ($240,000/12) | D25: =240000/12 -> 20000 | E25: =240000/12 -> 20000 | F25: =240000/12 -> 20000 | G25: =SUM(D25:F25) -> 60000
C27: Cash Disbursement for MOH | D27: =D23-D25 -> 55356.667 | E27: =E23-E25 -> 55636.667 | F27: =F23-F25 -> 54876.667 | G27: =G23-G25 -> 165870
